{
  "koreanNews": [
    {
      "id": "kr-1-1783202120258",
      "title": "월 수출 1천억달러가 고환율 때문?…\"패러다임 바뀌었다\"",
      "summary": "월 수출 1천억달러가 고환율 때문? 패러다임 바뀌었다. 반도체 중심의 수출 호조가 이어지면서 주요 시장 전반에서 증가 폭이 확대된 것으로 나타났다. 월초 수출 지표는 당월 전체 교역 흐름을 가늠하는 선행 자료로 활용되며, 주요 시장별 회복 속도를 함께 보여준다는 점에서 의미가 있다. 구체적으로 통상부에 따르면 지난달 반도체 수출은 1년 전 대비 199.5% 급증한 448억2천만달러로, 전체 수출의 43.8%를 차지한 것으로 파악된다. 배경으로는 2분기 평균 원/달러 환율이 28년 만에 1천500원선을 넘어서면서 일각에서는 고환율 덕에 수출이 늘어난 것 아니냐고 주장한다. 수출기업과 물류 담당자는 시장별 수요 변화와 통관 여건을 함께 확인하면서 계약 일정과 출하 계획을 보수적으로 조정할 필요가 있다.",
      "impact": "환율과 외환 흐름의 변화는 수출입 단가와 기업 실적 전망을 동시에 흔들 수 있어 무역 전략 재조정이 필요하다.",
      "source": "연합뉴스",
      "link": "https://www.yna.co.kr/view/AKR20260704035100003",
      "pubDate": 1783199701000
    },
    {
      "id": "kr-2-1783202121502",
      "title": "외인 156조 순매도에 원화가치 6%↓…24시 거래로 환율 안정될까",
      "summary": "외인 156조 순매도에 원화가치 6%↓ 24시 거래로 환율 안정될까. 이번 보도는 통상 규제와 공급망 변화가 실제 거래 조건과 수출 전략에 어떻게 연결되는지를 보여주는 사례로 볼 수 있다. 구체적으로 서정훈 하나은행 수석연구위원은 외국인 투자자의 순매도 여력이 50조90조원 가량 남아있을 것이라는 전망이 있다면서 적어도 8월 초까지는 지속되면서 환율이 1,500원대에 머무를 가능성이 크다고 말한 것으로 파악된다. 배경으로는 이낙원 농협은행 FX파생전문위원은 외국인 순매도가 지속되면서 7월 환율이 1,520원1,570원 선에 머무르다가 이후 미국 금리 인상으로 인플레이션이 꺾이고 외국인 리밸런싱이 마무리되면서 하반기 환율 하단이 1,470원 정도로 낮아질 것으로 예상된다고 말한 상황이다. 실무적으로는 수출 단가 산정, 원산지 검토, 미국향 투자와 생산 배분 전략을 다시 점검해야 한다는 뜻으로 해석된다.",
      "impact": "환율과 외환 흐름의 변화는 수출입 단가와 기업 실적 전망을 동시에 흔들 수 있어 무역 전략 재조정이 필요하다.",
      "source": "연합뉴스",
      "link": "https://www.yna.co.kr/view/AKR20260704030300002",
      "pubDate": 1783198381000
    },
    {
      "id": "kr-4-1783202136139",
      "title": "EU 철강 쿼터 절반 줄였는데…한국만 ‘예외 인정’ 선방한 이유",
      "summary": "EU 철강 쿼터 절반 줄였는데 한국만 예외 인정 선방한 이유. 국제 품목 분류 기준이 한국 측 주장대로 정리되면서 주요 시장에서 가격 경쟁력 개선이 기대된다. 품목 분류가 달라지면 동일 제품이라도 국가별 세율이 크게 달라질 수 있어 국제 기준 확정 자체가 수출 경쟁력과 직결된다. 구체적으로 나만의 AI 비서 정책 EU 무관세 쿼터 46% 축소 속 한국은 19.7% 줄어들어 선방FTA 체결국 우대中은 67% 급감 현대제철 당진제철소 냉연공장에 고부가가치 수출 품목인 냉연강판 코일이 겹겹이 쌓여 있다. 배경으로는 자유무역협정 두 개 이상의 국가들이 상품, 서비스, 투자 등 경제 분야에서 무역 장벽을 낮추거나 철폐하기로 맺는 협정이에요. 실무적으로는 수출 단가 산정, 원산지 검토, 미국향 투자와 생산 배분 전략을 다시 점검해야 한다는 뜻으로 해석된다.",
      "impact": "관세 정책 변화는 기업의 가격 경쟁력과 수출 채산성에 직접 영향을 주기 때문에 향후 주문과 투자 판단의 핵심 변수다.",
      "source": "매일경제",
      "link": "https://www.mk.co.kr/news/economy/12090359",
      "pubDate": 1783164030000
    },
    {
      "id": "kr-3-1783202122685",
      "title": "\"환율, 과거수준 복귀 어려워…금융사, 고환율 지속 대비해야\"",
      "summary": "환율, 과거수준 복귀 어려워 금융사, 고환율 지속 대비해야. 이번 보도는 통상 규제와 공급망 변화가 실제 거래 조건과 수출 전략에 어떻게 연결되는지를 보여주는 사례로 볼 수 있다. 배경으로는 환율은 이번 보고서 작성 이후 꾸준히 올라 전날까지 주간거래 종가 기준 34거래일째 1,500원대를 웃돌았고 지난 1일에는 장중 1,559.2원까지 치솟았다. 환율 민감도가 높은 업종은 결제 조건과 환헤지 전략을 조정하지 않으면 마진 변동성이 커질 수 있다. 환율은 이번 보고서 작성 이후 꾸준히 올라 전날까지 주간거래 종가 기준 34거래일째 1,500원대를 웃돌았고 지난 1일에는 장중 1,559.2원까지 치솟았다. 보고서에 따르면 환율은 2010년대 중반 이후 점진적인 상승세를 보이다가 2024년 상반기까지 대체로 1,200~1,300원대 범위에서 등락을 오갔다. 보고서가 작성된 시점은 지난 4월로, 당시 평균 환율은 주간거래 종가 기준 1,485.0원이었다. 박 연구위원은 보고서를 통해 환율 상승 압력이 높은 국면에 있으며, 이런 흐름이 내년 2월까지 지속될 것. 2024년 하반기 이후엔 일시적으로 1,300원대로 하락한 시기를 제외하고는 1,400~1,500원대를 유지하고 있는 상태다.",
      "impact": "환율과 외환 흐름의 변화는 수출입 단가와 기업 실적 전망을 동시에 흔들 수 있어 무역 전략 재조정이 필요하다.",
      "source": "연합뉴스",
      "link": "https://www.yna.co.kr/view/AKR20260703150300002",
      "pubDate": 1783123201000
    },
    {
      "id": "kr-5-1783202137632",
      "title": "“팔수록 손해, 요즘은 진짜”…고환율 직격탄 中企, 정부 15조 대출·보증",
      "summary": "팔수록 손해, 요즘은 진짜 고환율 직격탄 中企, 정부 15조 대출 보증. 반도체 중심의 수출 호조가 이어지면서 주요 시장 전반에서 증가 폭이 확대된 것으로 나타났다. 월초 수출 지표는 당월 전체 교역 흐름을 가늠하는 선행 자료로 활용되며, 주요 시장별 회복 속도를 함께 보여준다는 점에서 의미가 있다. 구체적으로 중동 상황 피해기업 정책금융 23조7000억원의 잔여 지원 여력 13조8000억원에 신규 자금 1조1000억원을 추가로 공급할 계획이다. 구체적으로 중소벤처기업진흥공단의 긴급경영안정자금 내에 고환율 등에 따른 경영애로 중소기업 전용 트랙을 신설한다. 배경으로는 중동 상황 피해기업 정책금융 23조7000억원의 잔여 지원 여력 13조8000억원에 신규 자금 1조1000억원을 추가로 공급할 계획이다. 구체적으로 중소벤처기업진흥공단의 긴급경영안정자금 내에 고환율 등에 따른 경영애로 중소기업 전용 트랙을 신설한다. 실무적으로는 수출 단가 산정, 원산지 검토, 미국향 투자와 생산 배분 전략을 다시 점검해야 한다는 뜻으로 해석된다.",
      "impact": "환율과 외환 흐름의 변화는 수출입 단가와 기업 실적 전망을 동시에 흔들 수 있어 무역 전략 재조정이 필요하다.",
      "source": "매일경제",
      "link": "https://www.mk.co.kr/news/economy/12090206",
      "pubDate": 1783112509000
    }
  ],
  "globalNews": [
    {
      "id": "gl-2-1783202127486",
      "title": "아시아의 대규모 무역 협정으로 트럼프 관세로 인한 피해 완화",
      "summary": "아시아의 대규모 무역 협정으로 트럼프 관세로 인한 피해 완화. 이번 보도는 통상 규제와 공급망 변화가 실제 거래 조건과 수출 전략에 어떻게 연결되는지를 보여주는 사례로 볼 수 있다. 배경으로는 도쿄 -- 거의 25년 동안 미국은 베트남 해산물 수출업체의 최고의 고객이었습니다. 무역 장벽과 관세 문제가 계속해서 제기됐지만 베트남 새우, 메기, 참치 등은 꾸준히 더 많은 미국 구매자를 찾았습니다. 실무적으로는 수출 단가 산정, 원산지 검토, 미국향 투자와 생산 배분 전략을 다시 점검해야 한다는 뜻으로 해석된다. 도쿄 -- 거의 25년 동안 미국은 베트남 해산물 수출업체의 최고의 고객이었습니다. 무역 장벽과 관세 문제가 계속해서 제기됐지만 베트남 새우, 메기, 참치 등은 꾸준히 더 많은 미국 구매자를 찾았습니다.",
      "impact": "관세 정책 변화는 기업의 가격 경쟁력과 수출 채산성에 직접 영향을 주기 때문에 향후 주문과 투자 판단의 핵심 변수다.",
      "source": "Nikkei Asia",
      "link": "https://asia.nikkei.com/spotlight/policy-asia/asia-s-big-trade-pacts-soften-damage-from-trump-tariffs",
      "pubDate": 1783202127486
    },
    {
      "id": "gl-1-1783202123306",
      "title": "Kioxia는 기술 선도가 줄어들면서 차세대 메모리 출하를 시작합니다.",
      "summary": "Kioxia는 기술 선도가 줄어들면서 차세대 메모리 출하를 시작합니다. 이번 보도는 통상 규제와 공급망 변화가 실제 거래 조건과 수출 전략에 어떻게 연결되는지를 보여주는 사례로 볼 수 있다. 배경으로는 반도체일본 제조업체가 삼성보다 우위에 있던 SK, 2년에서 1년으로 하락Kioxia는 이와테현 공장 확장 기념식에서 10세대 메모리 제품을 선보였습니다. SHUHEI OCHIAI 2026년 7월 4일 04 28 Kioxia Holdings가 최신 세대의 메모리 칩. 결국 이번 이슈는 통상 정책 변화가 계약 조건, 시장 접근성, 공급망 운영에 어떤 부담을 주는지 점검해야 한다는 신호로 읽힌다. 반도체일본 제조업체가 삼성보다 우위에 있던 SK, 2년에서 1년으로 하락Kioxia는 이와테현 공장 확장 기념식에서 10세대 메모리 제품을 선보였습니다. SHUHEI OCHIAI 2026년 7월 4일 04 28 Kioxia Holdings가 최신 세대의 메모리 칩.",
      "impact": "국제물류 비용과 운송 차질은 납기와 마진을 함께 압박해 글로벌 공급망 운영 전반에 부담을 준다.",
      "source": "Nikkei Asia",
      "link": "https://asia.nikkei.com/business/tech/semiconductors/kioxia-starts-shipping-next-gen-memory-as-technological-lead-shrinks",
      "pubDate": 1783202123306
    },
    {
      "id": "gl-3-1783202137742",
      "title": "미국, 북미 무역 협정 장기 갱신 막았다",
      "summary": "미국, 북미 무역 협정 장기 갱신 막았다. 이번 보도는 통상 규제와 공급망 변화가 실제 거래 조건과 수출 전략에 어떻게 연결되는지를 보여주는 사례로 볼 수 있다. 구체적으로 매년 약 2조 달러의 무역 규모를 뒷받침하는 이 협정은 해결되지 않은 분쟁으로 인해 압박을 받고 있습니다. 배경으로는 이번 마찰은 1994년 북미자유무역협정을 대체하는 USMCA가 발효된 지 6년 만에 발생한 상황이다. 결국 이번 이슈는 통상 정책 변화가 계약 조건, 시장 접근성, 공급망 운영에 어떤 부담을 주는지 점검해야 한다는 신호로 읽힌다. 이번 마찰은 1994년 북미자유무역협정을 대체하는 USMCA가 발효된 지 6년 만에 발생한 것으로 전해진다. 매년 약 2조 달러의 무역 규모를 뒷받침하는 이 협정은 해결되지 않은 분쟁으로 인해 압박을 받고 있습니다. 이 결정은 3국 무역 협정이 자동으로 16년 연장되는 기회를 놓치게 된다는 것을 의미합니다. 현재로서는 자유 무역 협정이 유효하지만 장기적인 약속이 부족하여 북미 전역에 새로운 경제적 불확실성이 발생하고 있습니다. 미국은 무역 관리들은 장기적인 연장을 약속하기 전에 큰 변화를 추진하고 있습니다.",
      "impact": "수출입 흐름 변화는 업종별 실적뿐 아니라 교역 상대국과의 통상 환경을 가늠하는 선행 신호로 볼 수 있다.",
      "source": "BBC News",
      "link": "https://www.bbc.co.uk/news/articles/ce8j2lmrvrdo?at_medium=RSS&at_campaign=rss",
      "pubDate": 1782932196000
    }
  ]
}